hatch_pip_deepfreeze/__init__.py
hatch_pip_deepfreeze/hooks.py
hatch_pip_deepfreeze/plugin.py
hatch_pip_deepfreeze-0.2.dist-info/METADATA
hatch_pip_deepfreeze-0.2.dist-info/WHEEL
hatch_pip_deepfreeze-0.2.dist-info/entry_points.txt
hatch_pip_deepfreeze-0.2.dist-info/licenses/LICENSE.txt
hatch_pip_deepfreeze-0.2.dist-info/RECORD
