Metadata-Version: 2.1
Name: hatch-pip-deepfreeze
Version: 0.2
Summary: Lock hatch environments using pip-deepfreeze
Project-URL: Documentation, https://github.com/sbidoul/hatch-pip-deepfreeze#readme
Project-URL: Issues, https://github.com/sbidoul/hatch-pip-deepfreeze/issues
Project-URL: Source, https://github.com/sbidoul/hatch-pip-deepfreeze
Author-email: Stéphane Bidoul <stephane.bidoul@acsone.eu>
License-File: LICENSE.txt
Classifier: Development Status :: 4 - Beta
Classifier: Framework :: Hatch
Classifier: Programming Language :: Python
Classifier: Programming Language :: Python :: 3.7
Classifier: Programming Language :: Python :: 3.8
Classifier: Programming Language :: Python :: 3.9
Classifier: Programming Language :: Python :: 3.10
Classifier: Programming Language :: Python :: 3.11
Classifier: Programming Language :: Python :: Implementation :: CPython
Classifier: Programming Language :: Python :: Implementation :: PyPy
Requires-Python: >=3.7
Requires-Dist: hatch
Requires-Dist: pip-deepfreeze
